pydanfossally/__init__.py
pydanfossally/const.py
pydanfossally/danfossallyapi.py
pydanfossally/exceptions.py
pydanfossally-0.0.34.dist-info/LICENSE
pydanfossally-0.0.34.dist-info/METADATA
pydanfossally-0.0.34.dist-info/WHEEL
pydanfossally-0.0.34.dist-info/top_level.txt
pydanfossally-0.0.34.dist-info/RECORD
