Metadata-Version: 2.1
Name: pydanfossally
Version: 0.0.34
Summary: Danfoss Ally API library
Home-page: https://github.com/mtrab/pydanfossally
Author: Malene Trab
Author-email: malene@trab.dk
License: MIT
Project-URL: Bug Tracker, https://github.com/mtrab/pydanfossally/issues
License-File: LICENSE
Requires-Dist: requests >=2.28.0
